.gitattributes
.gitignore
LICENSE
MANIFEST.in
README.rst
requirements.txt
setup.cfg
setup.py
versioneer.py
atomictempfile/__init__.py
atomictempfile/_version.py
atomictempfile/atomictempfile.py
atomictempfile.egg-info/PKG-INFO
atomictempfile.egg-info/SOURCES.txt
atomictempfile.egg-info/dependency_links.txt
atomictempfile.egg-info/entry_points.txt
atomictempfile.egg-info/pbr.json
atomictempfile.egg-info/requires.txt
atomictempfile.egg-info/top_level.txt
atomictempfile.egg-info/zip-safe
tests/__init__.py
tests/atomictemptfile_test.py