Metadata-Version: 1.1
Name: atomictempfile
Version: 0.2.post8
Summary: An atomic file write context manager
Home-page: https://github.com/clearclaw/atomictempfile
Author: J C Lawrence
Author-email: claw@kanga.nu
License: LGPL v3.0
Keywords: Atomic file write context manager
Platform: UNKNOWN
Classifier: Development Status :: 4 - Beta
Classifier: Intended Audience :: Developers
Classifier: License :: OSI Approved :: GNU Lesser General Public License v3 or later (LGPLv3+)
Classifier: Topic :: Utilities
